{
  "restaurantSlug": "sakura-sushi",
  "name": "Sakura Sushi",
  "description": "Sushi tươi mỗi ngày và món Nhật yêu thích - nigiri, sashimi, cuốn maki, donburi, mì nóng.",
  "cuisineType": "Nhật Bản",
  "logoUrl": "https://res.cloudinary.com/dtjl7hjbe/image/upload/v1761118786/yummyzoom/restaurants/sakura-sushi/profile/japanese-sushi-resta_e183fe12.jpg",
  "backgroundImageUrl": "https://res.cloudinary.com/dtjl7hjbe/image/upload/v1761118790/yummyzoom/restaurants/sakura-sushi/profile/Sushi_station_in_cli_48496d6b.jpg",
  "defaultCurrency": "VND",
  "isVerified": true,
  "isAcceptingOrders": true,
  "latitude": 21.001428,
  "longitude": 105.845131,
  "address": {
    "street": "456 Cherry Blossom Ave",
    "city": "Midtown",
    "state": "WA",
    "zipCode": "98101",
    "country": "USA"
  },
  "contact": {
    "phone": "+1 (555) 987-6543",
    "email": "hello@sakurasushi.com"
  },
  "businessHours": "10:30-21:30",
  "customizationGroups": [
    {
      "groupKey": "Sốt đậu nành",
      "minSelections": 1,
      "maxSelections": 1,
      "choices": [
        {
          "name": "Shoyu thường",
          "priceAdjustment": 0.0,
          "isDefault": true,
          "displayOrder": 1
        },
        {
          "name": "Shoyu ít muối",
          "priceAdjustment": 0.0,
          "isDefault": false,
          "displayOrder": 2
        }
      ]
    },
    {
      "groupKey": "Ăn thêm",
      "minSelections": 0,
      "maxSelections": 3,
      "choices": [
        {
          "name": "Thêm wasabi",
          "priceAdjustment": 5000.0,
          "isDefault": false,
          "displayOrder": 1
        },
        {
          "name": "Thêm gừng hồng",
          "priceAdjustment": 5000.0,
          "isDefault": false,
          "displayOrder": 2
        },
        {
          "name": "Sốt mayo cay",
          "priceAdjustment": 7000.0,
          "isDefault": false,
          "displayOrder": 3
        }
      ]
    },
    {
      "groupKey": "Số lượng cuốn",
      "minSelections": 1,
      "maxSelections": 1,
      "choices": [
        {
          "name": "6 miếng",
          "priceAdjustment": 0.0,
          "isDefault": true,
          "displayOrder": 1
        },
        {
          "name": "8 miếng",
          "priceAdjustment": 20000.0,
          "isDefault": false,
          "displayOrder": 2
        }
      ]
    }
  ],
  "menu": {
    "name": "Thực đơn chính",
    "description": "Gọi cả ngày",
    "categories": [
      {
        "name": "Khai vị",
        "displayOrder": 1,
        "items": [
          {
            "name": "Edamame",
            "description": "Đậu nành Nhật luộc, rắc muối biển",
            "basePrice": 49000.0,
            "imageUrl": "https://res.cloudinary.com/dtjl7hjbe/image/upload/v1761118793/yummyzoom/restaurants/sakura-sushi/menu-items/Edamame_on_a_bamboo__2f5d1e01.jpg",
            "isAvailable": true,
            "dietaryTags": [
              "Nhật",
              "Thuần chay",
              "Không gluten"
            ]
          },
          {
            "name": "Gyoza chiên",
            "description": "Há cảo Nhật áp chảo, sốt chấm",
            "basePrice": 69000.0,
            "imageUrl": "https://res.cloudinary.com/dtjl7hjbe/image/upload/v1761118795/yummyzoom/restaurants/sakura-sushi/menu-items/Gyoza_-_Tora_0a17ef30.jpg",
            "isAvailable": true
          },
          {
            "name": "Súp miso",
            "description": "Nước dùng kombu–katsuobushi, đậu phụ, rong biển",
            "basePrice": 39000.0,
            "imageUrl": "https://res.cloudinary.com/dtjl7hjbe/image/upload/v1761118798/yummyzoom/restaurants/sakura-sushi/menu-items/Miso_soup_e42211dc.jpg",
            "isAvailable": true
          },
          {
            "name": "Salad rong biển",
            "description": "Wakame giòn, mè rang, sốt gừng",
            "basePrice": 59000.0,
            "imageUrl": "https://res.cloudinary.com/dtjl7hjbe/image/upload/v1761120495/yummyzoom/restaurants/sakura-sushi/menu-items/Wakame_salad_cd9f4c60.jpg",
            "isAvailable": true,
            "dietaryTags": [
              "Nhật",
              "Thuần chay"
            ]
          },
          {
            "name": "Agedashi Tofu",
            "description": "Đậu phụ chiên xốt tsuyu, bonito/flakes",
            "basePrice": 69000.0,
            "imageUrl": "https://res.cloudinary.com/dtjl7hjbe/image/upload/v1761118806/yummyzoom/restaurants/sakura-sushi/menu-items/Agedashi_tofu_9582f014.jpg",
            "isAvailable": true,
            "dietaryTags": [
              "Nhật",
              "Chay"
            ]
          }
        ]
      },
      {
        "name": "Nigiri & Sashimi",
        "displayOrder": 2,
        "items": [
          {
            "name": "Nigiri cá hồi (2 miếng)",
            "description": "Cơm sushi + cá hồi tươi",
            "basePrice": 75000.0,
            "imageUrl": "https://res.cloudinary.com/dtjl7hjbe/image/upload/v1761118810/yummyzoom/restaurants/sakura-sushi/menu-items/Salmon_nigiri_5fb3f787.jpg",
            "isAvailable": true,
            "dietaryTags": [
              "Nhật",
              "Không gluten"
            ],
            "customizationGroups": [
              "Sốt đậu nành",
              "Ăn kèm"
            ]
          },
          {
            "name": "Nigiri cá ngừ (2 miếng)",
            "description": "Cơm sushi + cá ngừ đỏ",
            "basePrice": 79000.0,
            "imageUrl": "https://res.cloudinary.com/dtjl7hjbe/image/upload/v1761118813/yummyzoom/restaurants/sakura-sushi/menu-items/8nig_maguro_kihada_s_5e9d6aff.jpg",
            "isAvailable": true,
            "dietaryTags": [
              "Nhật",
              "Không gluten"
            ],
            "customizationGroups": [
              "Sốt đậu nành",
              "Ăn kèm"
            ]
          },
          {
            "name": "Nigiri tôm (2 miếng)",
            "description": "Cơm sushi + ebi luộc",
            "basePrice": 69000.0,
            "imageUrl": "https://res.cloudinary.com/dtjl7hjbe/image/upload/v1761118818/yummyzoom/restaurants/sakura-sushi/menu-items/Nigiri_Sushi_2647873_61410f8e.jpg",
            "isAvailable": true,
            "dietaryTags": [
              "Nhật",
              "Không gluten"
            ],
            "customizationGroups": [
              "Sốt đậu nành",
              "Ăn kèm"
            ]
          },
          {
            "name": "Nigiri trứng (2 miếng)",
            "description": "Cơm sushi + trứng cuộn",
            "basePrice": 59000.0,
            "imageUrl": "https://res.cloudinary.com/dtjl7hjbe/image/upload/v1761118823/yummyzoom/restaurants/sakura-sushi/menu-items/Nigiri_Sushi_2650509_de936725.jpg",
            "isAvailable": true,
            "dietaryTags": [
              "Chay"
            ],
            "customizationGroups": [
              "Sốt đậu nành",
              "Ăn kèm"
            ]
          },
          {
            "name": "Sashimi tổng hợp",
            "description": "Cá hồi, cá ngừ, bạch tuộc/tuỳ mùa",
            "basePrice": 219000.0,
            "imageUrl": "https://res.cloudinary.com/dtjl7hjbe/image/upload/v1761118829/yummyzoom/restaurants/sakura-sushi/menu-items/Sashimi_Moriawase_55a72d63.jpg",
            "isAvailable": true,
            "dietaryTags": [
              "Nhật",
              "Không gluten"
            ],
            "customizationGroups": [
              "Sốt đậu nành",
              "Ăn kèm"
            ]
          }
        ]
      },
      {
        "name": "Cuốn Maki & Rolls",
        "displayOrder": 3,
        "items": [
          {
            "name": "California Roll",
            "description": "Cua/giả cua, bơ, dưa leo, mè",
            "basePrice": 119000.0,
            "imageUrl": "https://res.cloudinary.com/dtjl7hjbe/image/upload/v1761118832/yummyzoom/restaurants/sakura-sushi/menu-items/California_roll_ecb263f6.jpg",
            "isAvailable": true,
            "customizationGroups": [
              "Số lượng cuốn",
              "Ăn kèm"
            ]
          },
          {
            "name": "Spicy Tuna Roll",
            "description": "Cá ngừ trộn mayo cay, hành lá",
            "basePrice": 129000.0,
            "imageUrl": "https://res.cloudinary.com/dtjl7hjbe/image/upload/v1761118839/yummyzoom/restaurants/sakura-sushi/menu-items/Spicy_tuna_roll_7472f4fe.jpg",
            "isAvailable": true,
            "customizationGroups": [
              "Số lượng cuốn",
              "Ăn kèm"
            ]
          },
          {
            "name": "Dragon Roll",
            "description": "Tôm tempura, bơ, sốt unagi trên mặt",
            "basePrice": 159000.0,
            "imageUrl": "https://res.cloudinary.com/dtjl7hjbe/image/upload/v1761118858/yummyzoom/restaurants/sakura-sushi/menu-items/Double_Dragon_Roll_b_3b229d0c.jpg",
            "isAvailable": true,
            "customizationGroups": [
              "Số lượng cuốn",
              "Ăn kèm"
            ]
          },
          {
            "name": "Kappa Maki (chay)",
            "description": "Cuộn dưa leo giòn, mè",
            "basePrice": 99000.0,
            "imageUrl": "https://res.cloudinary.com/dtjl7hjbe/image/upload/v1761118860/yummyzoom/restaurants/sakura-sushi/menu-items/8hosomak8_8a17511d.jpg",
            "isAvailable": true,
            "dietaryTags": [
              "Nhật",
              "Thuần chay"
            ],
            "customizationGroups": [
              "Số lượng cuốn",
              "Ăn kèm"
            ]
          }
        ]
      },
      {
        "name": "Donburi & Mì",
        "displayOrder": 4,
        "items": [
          {
            "name": "Chirashi Don",
            "description": "Cơm sushi phủ sashimi tổng hợp",
            "basePrice": 199000.0,
            "imageUrl": "https://res.cloudinary.com/dtjl7hjbe/image/upload/v1761118868/yummyzoom/restaurants/sakura-sushi/menu-items/Chirashi-zushi_769cdd4d.jpg",
            "isAvailable": true
          },
          {
            "name": "Salmon Don",
            "description": "Cơm sushi phủ cá hồi tươi",
            "basePrice": 179000.0,
            "imageUrl": "https://res.cloudinary.com/dtjl7hjbe/image/upload/v1761118873/yummyzoom/restaurants/sakura-sushi/menu-items/Chum_salmonsake-ikur_ec547f7b.jpg",
            "isAvailable": true
          },
          {
            "name": "Udon nóng",
            "description": "Nước dùng nhẹ, hành lá, chả cá/đậu phụ",
            "basePrice": 129000.0,
            "imageUrl": "https://res.cloudinary.com/dtjl7hjbe/image/upload/v1761118877/yummyzoom/restaurants/sakura-sushi/menu-items/TEMPURA_UDON_KISHIME_198c1cc3.jpg",
            "isAvailable": true
          }
        ]
      },
      {
        "name": "Tráng miệng",
        "displayOrder": 5,
        "items": [
          {
            "name": "Kem mochi (2 viên)",
            "description": "Mochi lạnh nhân kem – vị theo ngày",
            "basePrice": 69000.0,
            "imageUrl": "https://res.cloudinary.com/dtjl7hjbe/image/upload/v1761118881/yummyzoom/restaurants/sakura-sushi/menu-items/Mochi_Ice_Cream_1720b9a3.jpg",
            "isAvailable": true,
            "dietaryTags": [
              "Nhật",
              "Chay"
            ]
          },
          {
            "name": "Bánh phô mai matcha",
            "description": "Cheesecake vị trà xanh",
            "basePrice": 79000.0,
            "imageUrl": "https://res.cloudinary.com/dtjl7hjbe/image/upload/v1761118885/yummyzoom/restaurants/sakura-sushi/menu-items/Julias_Japanese_Gree_013ce9d3.jpg",
            "isAvailable": true
          }
        ]
      },
      {
        "name": "Đồ uống",
        "displayOrder": 6,
        "items": [
          {
            "name": "Trà xanh nóng",
            "description": "Matcha ấm, thanh nhẹ",
            "basePrice": 29000.0,
            "imageUrl": "https://res.cloudinary.com/dtjl7hjbe/image/upload/v1761118890/yummyzoom/restaurants/sakura-sushi/menu-items/Hot_Matcha_Green_Tea_8ae246a7.jpg",
            "isAvailable": true
          },
          {
            "name": "Matcha latte đá",
            "description": "Matcha, sữa, đá – thơm béo",
            "basePrice": 49000.0,
            "imageUrl": "https://res.cloudinary.com/dtjl7hjbe/image/upload/v1761118895/yummyzoom/restaurants/sakura-sushi/menu-items/Matcha_latte_7387a02c.jpg",
            "isAvailable": true
          },
          {
            "name": "Ramune",
            "description": "Soda Nhật chai bi tròn",
            "basePrice": 45000.0,
            "imageUrl": "https://res.cloudinary.com/dtjl7hjbe/image/upload/v1761118899/yummyzoom/restaurants/sakura-sushi/menu-items/Ramune_melon_flavor_3b220384.jpg",
            "isAvailable": true
          },
          {
            "name": "Nước khoáng có ga",
            "description": "Uống lạnh với lát chanh",
            "basePrice": 39000.0,
            "imageUrl": "https://res.cloudinary.com/dtjl7hjbe/image/upload/v1761118755/yummyzoom/restaurants/el-camino-taqueria/menu-items/Sparkling_Water_with_9cce3fc8.jpg",
            "isAvailable": true
          }
        ]
      }
    ]
  }
}